miraihttpapi/Configer.py
miraihttpapi/MessageChain.py
miraihttpapi/MiraiCore.py
miraihttpapi/__init__.py
miraihttpapi-1.3.dist-info/METADATA
miraihttpapi-1.3.dist-info/WHEEL
miraihttpapi-1.3.dist-info/top_level.txt
miraihttpapi-1.3.dist-info/RECORD
